Modules/phase_accumulator/phase_accumulator.v
module phase_accumulator(clk, reset, mode, fph, word, phase);
    parameter M = 48;
    parameter N = 14;

    input clk, reset, fph;
    input [1:0] mode;
    inout [M-1:0] word;
    output [N-1:0] phase;

    reg [M-1:0] freq, acc;

    assign phase = acc[M-1:M-N];
    assign word  = mode == 2'b10 ? (fph ? freq : acc) : 'bz;

    always @ (posedge clk, posedge reset)
    begin
        if (reset) begin
            freq  <= 'b0;
            acc   <= 'b0;
        end
        else begin
            if (!mode)
                acc <= acc + freq;
            else if (mode == 2'b11) begin
                if (fph)
                    freq <= word;
                else
                    acc  <= word;
            end
        end
    end

endmodule

Modules/phase_accumulator/phase_accumulator_tb.v
`include "phase_accumulator/phase_accumulator.v"
`timescale 1ns/100ps

module phase_accumulator_tb;
    reg clk, reset, fph;
    reg [1:0] mode;
    reg [4:0] temp;

    wire [3:0] phase;
    wire [4:0] word;

    assign word = mode == 2'b10 ? 'bz : temp;

    phase_accumulator #(.M(5), .N(4)) U2_pa_tb (
        .clk    (clk),
        .reset  (reset),
        .mode   (mode),
        .fph    (fph),
        .word   (word),
        .phase  (phase)
    );

    initial begin
        $dumpfile ("phase_accumulator/output/phase_accumulator.vcd");

        clk   = 0;
        reset = 0;
        temp  = 5;
        mode  = 'b0;
        fph   = 0;

        $dumpvars;
        #9 $finish;
    end

    always begin
        #0.5 clk = ~clk;
    end

    initial begin
        #0.6 reset = 1;
        #0.4 reset = 0;

        #0.5 mode  = 2'b11;
             fph   = 1;

        #1   fph   = 0;
             temp  = 2;

        #1   mode  = 2'b10;
             fph   = 1;
             temp  = 'b0;

        #1   mode  = 'b0;
             temp  = 1;

        #2   mode  = 2'b01;

        #1   mode  = 'b0;
    end

endmodule

Modules/phase_accumulator/output/phase_accumulator.vcd
$date
	Thu Sep 12 17:14:17 2019
$end
$version
	Icarus Verilog
$end
$timescale
	100ps
$end
$scope module phase_accumulator_tb $end
$var wire 5 ! word [4:0] $end
$var wire 4 " phase [3:0] $end
$var reg 1 # clk $end
$var reg 1 $ fph $end
$var reg 2 % mode [1:0] $end
$var reg 1 & reset $end
$var reg 5 ' temp [4:0] $end
$scope module U2_pa_tb $end
$var wire 1 # clk $end
$var wire 1 $ fph $end
$var wire 2 ( mode [1:0] $end
$var wire 1 & reset $end
$var wire 5 ) word [4:0] $end
$var wire 4 * phase [3:0] $end
$var reg 5 + acc [4:0] $end
$var reg 5 , freq [4:0] $end
$upscope $end
$upscope $end
$enddefinitions $end
#0
$dumpvars
bx ,
bx +
bx *
b101 )
b0 (
b101 '
0&
b0 %
0$
0#
bx "
b101 !
$end
#5
1#
#6
b0 "
b0 *
b0 +
b0 ,
1&
#10
0&
0#
#15
b101 ,
1$
b11 %
b11 (
1#
#20
0#
#25
b1 "
b1 *
b10 +
b10 !
b10 )
1#
b10 '
0$
#30
0#
#35
b101 !
b101 )
1#
b0 '
1$
b10 %
b10 (
#40
0#
#45
b11 "
b11 *
b111 +
b1 !
b1 )
1#
b1 '
b0 %
b0 (
#50
0#
#55
b110 "
b110 *
b1100 +
1#
#60
0#
#65
1#
b1 %
b1 (
#70
0#
#75
b1000 "
b1000 *
b10001 +
1#
b0 %
b0 (
#80
0#
#85
b1011 "
b1011 *
b10110 +
1#
