Modules/phase_accumulator/phase_accumulator.v
module phase_accumulator(clk, reset, mode, fph, word, phase);
    parameter M = 48;
    parameter N = 14;

    input clk, reset, fph;
    input [1:0] mode;
    inout [M-1:0] word;
    output [N-1:0] phase;

    reg [M-1:0] freq, acc;

    assign phase = acc[M-1:M-N];
    assign word  = mode == 2'b10 ? (fph ? freq : acc) : 'bz;

    always @ (posedge clk, posedge reset)
    begin
        if (reset) begin
            freq  <= 'b0;
            acc   <= 'b0;
        end
        else begin
            if (!mode)
                acc <= acc + freq;
            else if (mode == 2'b11) begin
                if (fph)
                    freq <= word;
                else
                    acc  <= word;
            end
        end
    end

endmodule

Modules/serial_peripheral_interface/spi.v
module spi(sclk, mosi, miso, ss, wordin, wordout, load, br);
parameter B = 8;

input sclk, mosi, ss, load;
input [B-1:0] wordin;
output miso, br;
output [B-1:0] wordout;

reg [B-1:0] buffer;
reg [$clog2(B)-1:0] counter;

assign br      = !ss ? !counter : 'bz;
assign wordout = !ss ? buffer : 'bz;
assign miso    = !ss ? buffer[0] : 'bz;

always @(posedge sclk, posedge ss) begin
    if (ss) begin
        counter <= 'b0;
    end
    else begin
        if (load && !counter)
            buffer <= wordin;
        else
            buffer <= {mosi, buffer[B-1:1]};
        
        counter <= counter + 1;
    end
end

endmodule

Modules/operation_profile_configurator/opc.v
`include "serial_peripheral_interface/spi.v"
`include "phase_accumulator/phase_accumulator.v"

module opc(clk, sclk, reset, mosi, miso, ss, br, outr, phase);
    parameter M = 48;
    parameter N = 14;
    parameter B = 8;

    input clk, sclk, reset, mosi, ss;
    output miso, br, outr;
    output [N-1:0] phase;
    
    reg fph;
    reg [1:0] mode;
    reg [M-1:0] buffer;
    reg [$clog2(M/B+2)-1:0] counter;

    wire [B-1:0] word_read;
    wire [M-1:0] pa_word;

    assign pa_word = mode == 2'b10 || counter != 3'b111 ? 'bz : buffer;
    assign outr    = !mode;

    spi #(.B(B)) U1_spi (
        .sclk       (sclk),
        .mosi       (mosi),
        .miso       (miso),
        .ss         (ss),
        .wordin     (buffer[B-1:0]),
        .wordout    (word_read),
        .load       (mode == 2'b10),
        .br         (br)
    );

    phase_accumulator #(.M(M), .N(N)) U2_pa (
        .clk        (clk),
        .reset      (reset),
        .mode       (~(~mode)),
        .fph        (fph),
        .word       (pa_word),
        .phase      (phase)
    );

    always @(posedge sclk, posedge reset) begin
        if (reset) begin
            fph     = 1'b0;
            mode    = 2'b01;
            buffer  =  'b0;
            counter = 3'b111;
        end
        else begin
            if (!ss) begin
                if (br) begin
                    counter = counter + 1;
                    if (counter == 3'b000) begin
                        mode = 2'b01;
                    end
                    else if (counter == 3'b001) begin
                        mode[1] = word_read[7];
                        mode[0] = word_read[7] ? word_read[6] : word_read[4];
                        fph = word_read[5];
                    end
                    else begin
                        if (mode[1]) begin
                            buffer = buffer >> B;
                            if (mode[0]) begin
                                buffer[M-1:M-B] = word_read;
                            end
                        end
                    end
                end

                if (counter == 3'b001 && mode == 2'b10) begin
                    buffer = pa_word;
                end
            end
            else begin
                counter = 3'b111;
            end
        end
    end

endmodule

Modules/operation_profile_configurator/opc_tb.v
`include "operation_profile_configurator/opc.v"
`timescale 1ns/100ps

module opc_tb;
    reg clk, sclk, reset, mosi, ss;
    wire miso, br, outr;
    wire [13:0] phase;

    opc #(.M(48), .N(14), .B(8)) U3_opc_tb (
        .clk        (clk),
        .sclk       (sclk),
        .reset      (reset),
        .mosi       (mosi),
        .miso       (miso),
        .ss         (ss),
        .br         (br),
        .outr       (outr),
        .phase      (phase)
    );

    initial begin
        $dumpfile ("operation_profile_configurator/output/opc.vcd");
        
        clk     = 0;
        sclk    = 0;
        reset   = 0;
        mosi    = 0;
        ss      = 1;
        
        $dumpvars;
        $finish;
    end

    always begin
        #0.5 clk = ~clk;
    end

    always begin
        #1 sclk = ~sclk;
    end

    initial begin
        #0.2 reset  = 1;
        #0.3 reset  = 0;
             ss     = 0;

        //Instruction Byte 1
        //Write to freq
        #0.5 mosi   = 0;
        #2   mosi   = 0;
        #2   mosi   = 0;
        #2   mosi   = 0;
        #2   mosi   = 0;
        #2   mosi   = 1;
        #2   mosi   = 1;
        #2   mosi   = 1;

        //Frequency
        #2 mosi  = 1;
        #2 mosi  = 0;
        #2 mosi  = 0;
        #2 mosi  = 0;
        #2 mosi  = 0;
        #2 mosi  = 0;
        #2 mosi  = 0;
        #2 mosi  = 0;

        #2 mosi  = 0;
        #2 mosi  = 0;
        #2 mosi  = 0;
        #2 mosi  = 0;
        #2 mosi  = 0;
        #2 mosi  = 0;
        #2 mosi  = 0;
        #2 mosi  = 0;

        #2 mosi  = 0;
        #2 mosi  = 0;
        #2 mosi  = 0;
        #2 mosi  = 0;
        #2 mosi  = 0;
        #2 mosi  = 0;
        #2 mosi  = 0;
        #2 mosi  = 0;

        #2 mosi  = 0;
        #2 mosi  = 0;
        #2 mosi  = 0;
        #2 mosi  = 0;
        #2 mosi  = 0;
        #2 mosi  = 0;
        #2 mosi  = 0;
        #2 mosi  = 0;

        #2 mosi  = 0;
        #2 mosi  = 0;
        #2 mosi  = 0;
        #2 mosi  = 0;
        #2 mosi  = 0;
        #2 mosi  = 0;
        #2 mosi  = 0;
        #2 mosi  = 0;

        #2 mosi  = 1;
        #2 mosi  = 0;
        #2 mosi  = 0;
        #2 mosi  = 0;
        #2 mosi  = 0;
        #2 mosi  = 0;
        #2 mosi  = 0;
        #2 mosi  = 0;

        //Sync Byte
        #2 mosi  = 0;
        #14

        //Instruction Byte 2
        //Write to acc
        #2 mosi  = 0;
        #2 mosi  = 0;
        #2 mosi  = 0;
        #2 mosi  = 0;
        #2 mosi  = 0;
        #2 mosi  = 0;
        #2 mosi  = 1;
        #2 mosi  = 1;

        //Phase Offset
        #2 mosi  = 0;
        #2 mosi  = 0;
        #2 mosi  = 1;
        #2 mosi  = 0;
        #2 mosi  = 0;
        #2 mosi  = 0;
        #2 mosi  = 0;
        #2 mosi  = 0;

        #2 mosi  = 1;
        #2 mosi  = 0;
        #2 mosi  = 1;
        #2 mosi  = 1;
        #2 mosi  = 1;
        #2 mosi  = 1;
        #2 mosi  = 0;
        #2 mosi  = 0;

        #2 mosi  = 0;
        #2 mosi  = 1;
        #2 mosi  = 1;
        #2 mosi  = 1;
        #2 mosi  = 0;
        #2 mosi  = 1;
        #2 mosi  = 0;
        #2 mosi  = 0;

        #2 mosi  = 0;
        #2 mosi  = 0;
        #2 mosi  = 0;
        #2 mosi  = 0;
        #2 mosi  = 0;
        #2 mosi  = 0;
        #2 mosi  = 0;
        #2 mosi  = 0;

        #2 mosi  = 0;
        #2 mosi  = 0;
        #2 mosi  = 0;
        #2 mosi  = 0;
        #2 mosi  = 0;
        #2 mosi  = 0;
        #2 mosi  = 0;
        #2 mosi  = 1;

        #2 mosi  = 0;
        #2 mosi  = 0;
        #2 mosi  = 0;
        #2 mosi  = 0;
        #2 mosi  = 0;
        #2 mosi  = 0;
        #2 mosi  = 0;
        #2 mosi  = 0;

        //Sync Byte
        #2 mosi  = 0;
        #14

        //Instruction Byte 3
        //Read from freq
        #2 mosi  = 0;
        #2 mosi  = 0;
        #2 mosi  = 0;
        #2 mosi  = 0;
        #2 mosi  = 0;
        #2 mosi  = 1;
        #2 mosi  = 0;
        #2 mosi  = 1;

        //Sync Byte
        //Reads garbage
        #16

        //Data read
        #96 ;
    end
endmodule

Modules/operation_profile_configurator/output/opc.vcd
$date
	Fri Sep 13 00:03:21 2019
$end
$version
	Icarus Verilog
$end
$timescale
	100ps
$end
$scope module opc_tb $end
$var wire 14 ! phase [13:0] $end
$var wire 1 " outr $end
$var wire 1 # miso $end
$var wire 1 $ br $end
$var reg 1 % clk $end
$var reg 1 & mosi $end
$var reg 1 ' reset $end
$var reg 1 ( sclk $end
$var reg 1 ) ss $end
$scope module U3_opc_tb $end
$var wire 1 % clk $end
$var wire 1 & mosi $end
$var wire 48 * pa_word [47:0] $end
$var wire 1 ' reset $end
$var wire 1 ( sclk $end
$var wire 1 ) ss $end
$var wire 8 + word_read [7:0] $end
$var wire 14 , phase [13:0] $end
$var wire 1 " outr $end
$var wire 1 # miso $end
$var wire 1 $ br $end
$var reg 48 - buffer [47:0] $end
$var reg 3 . counter [2:0] $end
$var reg 1 / fph $end
$var reg 2 0 mode [1:0] $end
$scope module U1_spi $end
$var wire 1 1 load $end
$var wire 1 & mosi $end
$var wire 1 ( sclk $end
$var wire 1 ) ss $end
$var wire 8 2 wordin [7:0] $end
$var wire 8 3 wordout [7:0] $end
$var wire 1 # miso $end
$var wire 1 $ br $end
$var reg 8 4 buffer [7:0] $end
$var reg 3 5 counter [2:0] $end
$upscope $end
$scope module U2_pa $end
$var wire 1 % clk $end
$var wire 1 / fph $end
$var wire 2 6 mode [1:0] $end
$var wire 1 ' reset $end
$var wire 48 7 word [47:0] $end
$var wire 14 8 phase [13:0] $end
$var reg 48 9 acc [47:0] $end
$var reg 48 : freq [47:0] $end
$upscope $end
$upscope $end
$upscope $end
$enddefinitions $end
#3660
$dumpvars
b10000000000000000000000000000000000000001 :
b1000000000000000001011100011110100000100 9
b100000 8
b10000000000000000000000000000000000000001 7
b10 6
b111 5
b11111100 4
b11111100 3
b1 2
11
b10 0
1/
b110 .
b1 -
b100000 ,
b11111100 +
b10000000000000000000000000000000000000001 *
0)
0(
0'
1&
0%
0$
0#
0"
b100000 !
$end
#3665
1%
#3670
1$
b11111110 +
b11111110 3
b0 5
b11111110 4
0%
1(
#3675
1%
#3680
0%
0(
#3685
1%
#3690
1#
0$
b1 +
b1 3
b1 5
b1 4
b0 2
b0 -
b111 .
0%
1(
#3695
1%
#3700
0%
0(
#3705
1%
#3710
0#
b10000000 +
b10000000 3
b10 5
b10000000 4
0%
1(
#3715
1%
#3720
0%
0(
#3725
1%
#3730
b11000000 +
b11000000 3
b11 5
b11000000 4
0%
1(
#3735
1%
#3740
0%
0(
#3745
1%
#3750
b11100000 +
b11100000 3
b100 5
b11100000 4
0%
1(
#3755
1%
#3760
0%
0(
#3765
1%
#3770
b11110000 +
b11110000 3
b101 5
b11110000 4
0%
1(
#3775
1%
#3780
0%
0(
#3785
1%
#3790
b11111000 +
b11111000 3
b110 5
b11111000 4
0%
1(
#3795
1%
#3800
0%
0(
#3805
1%
#3810
b11111100 +
b11111100 3
b111 5
b11111100 4
0%
1(
#3815
1%
#3820
0%
0(
#3825
1%
#3830
1$
b11111110 +
b11111110 3
b0 5
b11111110 4
0%
1(
#3835
1%
#3840
0%
0(
#3845
1%
#3850
1#
0$
b11111111 +
b11111111 3
b1 5
b11111111 4
bz *
bz 7
b1 6
01
b1 0
b0 .
0%
1(
